slofop/__init__.py
slofop/filesystem_handlers.py
slofop/slofop.py
slofop/util.py
slofop-0.3.0.dist-info/WHEEL
slofop-0.3.0.dist-info/METADATA
slofop-0.3.0.dist-info/RECORD
