Metadata-Version: 2.1
Name: slofop
Version: 0.3.0
Summary: A relatively simple and good-looking logging library for Python, with relatively good customisability.
Home-page: https://github.com/PaddeCraft/slofop
Author: PaddeCraft
Author-email: paddecraft@gmail.com
Requires-Python: >=3.10,<4.0
Classifier: Programming Language :: Python :: 3
Classifier: Programming Language :: Python :: 3.10
Classifier: Programming Language :: Python :: 3.11
Requires-Dist: rich (>=12.6.0,<13.0.0)
Project-URL: Repository, https://github.com/PaddeCraft/slofop
